sheriff/__init__.py
sheriff/gui.py
sheriff/gui_data/data/HaarCascadeClassifier.xml
sheriff/gui_data/res/bg.png
sheriff/gui_data/res/logo.ico
sheriff/gui_data/res/logo.png
sheriff/gui_data/res/font/KeepCalm-Medium.ttf
sheriff/gui_data/scripts/app.ui
sheriff-1.6.dist-info/LICENSE.txt
sheriff-1.6.dist-info/METADATA
sheriff-1.6.dist-info/WHEEL
sheriff-1.6.dist-info/top_level.txt
sheriff-1.6.dist-info/RECORD
