Metadata-Version: 2.1
Name: sheriff
Version: 1.6
Summary: An AI enabled program to detect car speed
Home-page: https://github.com/Programming-Hero-1313/Sheriff
Author: Gautam Gambhir
Author-email: Gautam Gambhir <ggambhir1919@gmail.com>
Project-URL: Homepage, https://github.com/Programming-Hero-1313/Sheriff
Project-URL: Bug Tracker, https://github.com/Programming-Hero-1313/Sheriff/issues
Keywords: speed detector,sheriff,ai,opencv
Classifier: Programming Language :: Python :: 3
Classifier: License :: OSI Approved :: MIT License
Classifier: Operating System :: OS Independent
Requires-Python: >=3.10
License-File: LICENSE.txt
Requires-Dist: colorama
Requires-Dist: numpy
Requires-Dist: opencv-python
Requires-Dist: Pillow
Requires-Dist: PyQt5
Requires-Dist: PySide6
Requires-Dist: regex
